pygimp/cli.py
pygimp/init.py
pygimp/pygimp_core.py
pygimp_labs-0.2.4.dist-info/METADATA
pygimp_labs-0.2.4.dist-info/WHEEL
pygimp_labs-0.2.4.dist-info/entry_points.txt
pygimp_labs-0.2.4.dist-info/RECORD
