Metadata-Version: 2.1
Name: pygimp-labs
Version: 0.2.4
Summary: PythonでGIMPスクリプトを操作するためのパッケージ
Author: Maki
Author-email: sunwood.ai.labs@gmail.com
Requires-Python: >=3.8,<4.0
Classifier: Programming Language :: Python :: 3
Classifier: Programming Language :: Python :: 3.8
Classifier: Programming Language :: Python :: 3.9
Classifier: Programming Language :: Python :: 3.10
Classifier: Programming Language :: Python :: 3.11
Classifier: Programming Language :: Python :: 3.12
Requires-Dist: art (>=6.2,<7.0)
Requires-Dist: loguru (>=0.7.2,<0.8.0)
